linecard/__init__.py
linecard/linecard_parsing.cp312-win32.pyd
linecard/linecard_parsing.pyi
linecard-0.2.0.post1.dist-info/licenses/LICENSE
linecard-0.2.0.post1.dist-info/METADATA
linecard-0.2.0.post1.dist-info/WHEEL
linecard-0.2.0.post1.dist-info/top_level.txt
linecard-0.2.0.post1.dist-info/RECORD
