Metadata-Version: 2.4
Name: linecard
Version: 0.2.0.post1
Author-email: KarisAya <karisaya@foxmail.com>
Requires-Python: >=3.12
License-File: LICENSE
Requires-Dist: pillow<12.0.0,>=11.1.0
Requires-Dist: fonttools<5.0.0,>=4.58.0
Dynamic: license-file
